Metadata-Version: 1.0
Name: fastrequest789
Version: 1.0.0
Summary: fast requests
Home-page: https://github.com/ayong1/-
Author: ayong01
Author-email: 13026391531@163.com
License: MIT Licence
Keywords: pip,requests,aiohttp,spider
Platform: any
